<env:Envelope xmlns:env="http://www.w3.org/2003/05/soap-envelope"><env:Header xmlns:wsa="http://www.w3.org/2005/08/addressing"><wsa:To env:mustUnderstand="true">http://www.w3.org/2005/08/addressing/anonymous</wsa:To><wsa:Action>http://ns.electronichealth.net.au/pcehr/svc/RemoveDocument/1.1/RemoveDocumentPortType/Fault/standardError</wsa:Action><wsa:MessageID>17d662a0-ffa3-4cf0-a8c7-08fbdf8e62e2</wsa:MessageID><wsa:RelatesTo>urn:uuid:2cbf0b72-e95d-4c50-9d0e-46485df2aad3</wsa:RelatesTo></env:Header><env:Body><env:Fault><env:Code><env:Value>env:Sender</env:Value></env:Code><env:Reason><env:Text xml:lang="en-AU">PCEHR_ERROR</env:Text></env:Reason><env:Detail><ns2:standardError xmlns:ns2="http://ns.electronichealth.net.au/wsp/xsd/StandardError/2010"><ns2:errorCode>badlyFormedMsg</ns2:errorCode><ns2:message>PCEHR_ERROR_0510 - SOAP body fault</ns2:message></ns2:standardError></env:Detail></env:Fault></env:Body></env:Envelope>